pytyk/__init__.py
pytyk/services.py
pytyk/tyk_exceptions.py
pytyk-0.1.2.dist-info/AUTHORS.rst
pytyk-0.1.2.dist-info/LICENSE
pytyk-0.1.2.dist-info/METADATA
pytyk-0.1.2.dist-info/WHEEL
pytyk-0.1.2.dist-info/top_level.txt
pytyk-0.1.2.dist-info/RECORD
