Metadata-Version: 2.1
Name: pytyk
Version: 0.1.2
Summary: A python package to handle the resources of the Tyk API Gateway
Home-page: https://github.com/maritza05/pytyk
Author: Maritza Esparza
Author-email: maritzaesparza05@gmail.com
License: MIT license
Keywords: pytyk
Platform: UNKNOWN
Classifier: Development Status :: 2 - Pre-Alpha
Classifier: Intended Audience :: Developers
Classifier: License :: OSI Approved :: MIT License
Classifier: Natural Language :: English
Classifier: Programming Language :: Python :: 2
Classifier: Programming Language :: Python :: 2.7
Classifier: Programming Language :: Python :: 3
Classifier: Programming Language :: Python :: 3.4
Classifier: Programming Language :: Python :: 3.5
Classifier: Programming Language :: Python :: 3.6
Classifier: Programming Language :: Python :: 3.7
